slumber-stubs/METADATA.toml
slumber-stubs/__init__.pyi
slumber-stubs/exceptions.pyi
slumber-stubs/serialize.pyi
slumber-stubs/utils.pyi
types_slumber-0.7.3.5.dist-info/METADATA
types_slumber-0.7.3.5.dist-info/WHEEL
types_slumber-0.7.3.5.dist-info/top_level.txt
types_slumber-0.7.3.5.dist-info/RECORD
